ubase.py
ubase-0.2.1.dist-info/LICENSE
ubase-0.2.1.dist-info/WHEEL
ubase-0.2.1.dist-info/METADATA
ubase-0.2.1.dist-info/RECORD
